factory_boss/__init__.py
factory_boss/entity.py
factory_boss/errors.py
factory_boss/generator.py
factory_boss/grammar.py
factory_boss/instance.py
factory_boss/reference_resolver.py
factory_boss/relation_maker.py
factory_boss/scripts/generate.py
factory_boss/spec_parser/__init__.py
factory_boss/spec_parser/parser.py
factory_boss/spec_parser/value_spec_registry.py
factory_boss/value_spec.py
factory_boss-0.1.0.dist-info/LICENSE
factory_boss-0.1.0.dist-info/WHEEL
factory_boss-0.1.0.dist-info/METADATA
factory_boss-0.1.0.dist-info/RECORD
