Metadata-Version: 2.1
Name: factory-boss
Version: 0.1.0
Summary: Fake entire data schemas.
Home-page: https://github.com/mariushelf/factory_boss
License: MIT
Author: Marius Helf
Author-email: helfsmarius@gmail.com
Requires-Python: >=3.7,<4.0
Classifier: Development Status :: 3 - Alpha
Classifier: License :: OSI Approved :: MIT License
Classifier: Programming Language :: Python :: 3
Classifier: Programming Language :: Python :: 3.10
Classifier: Programming Language :: Python :: 3.7
Classifier: Programming Language :: Python :: 3.8
Classifier: Programming Language :: Python :: 3.9
Classifier: Programming Language :: Python :: Implementation :: PyPy
Requires-Dist: Faker (>=8.1.4,<9.0.0)
Requires-Dist: PyYAML (>=5.4.1,<6.0.0)
Requires-Dist: graphlib_backport (>=1.0.0,<2.0.0); python_version < "3.9"
Requires-Dist: lark (>=0.11.3,<0.12.0)
Project-URL: Documentation, https://github.com/mariushelf/factory_boss
Project-URL: Repository, https://github.com/mariushelf/factory_boss
